jupyterlab_fasta/__init__.py
jupyterlab_fasta/_version.py
jupyterlab_fasta-3.3.0.data/data/share/jupyter/labextensions/@jupyterlab/fasta-extension/package.json
jupyterlab_fasta-3.3.0.data/data/share/jupyter/labextensions/@jupyterlab/fasta-extension/static/216.4fdb3cb423aec0a0b294.js
jupyterlab_fasta-3.3.0.data/data/share/jupyter/labextensions/@jupyterlab/fasta-extension/static/410.a7e6b5eae966dbeb7f67.js
jupyterlab_fasta-3.3.0.data/data/share/jupyter/labextensions/@jupyterlab/fasta-extension/static/410.a7e6b5eae966dbeb7f67.js.LICENSE.txt
jupyterlab_fasta-3.3.0.data/data/share/jupyter/labextensions/@jupyterlab/fasta-extension/static/568.b32ebcf7155378c65c70.js
jupyterlab_fasta-3.3.0.data/data/share/jupyter/labextensions/@jupyterlab/fasta-extension/static/643.929c653e8b3ed3e6bb69.js
jupyterlab_fasta-3.3.0.data/data/share/jupyter/labextensions/@jupyterlab/fasta-extension/static/remoteEntry.b15a25cb741a6c7381f8.js
jupyterlab_fasta-3.3.0.data/data/share/jupyter/labextensions/@jupyterlab/fasta-extension/static/style.js
jupyterlab_fasta-3.3.0.data/data/share/jupyter/labextensions/@jupyterlab/fasta-extension/static/third-party-licenses.json
jupyterlab_fasta-3.3.0.data/data/share/jupyter/labextensions/@jupyterlab/fasta-extension/install.json
jupyterlab_fasta-3.3.0.dist-info/METADATA
jupyterlab_fasta-3.3.0.dist-info/WHEEL
jupyterlab_fasta-3.3.0.dist-info/licenses/LICENSE
jupyterlab_fasta-3.3.0.dist-info/RECORD
